setup.py
wxgfuntest/__init__.py
wxgfuntest/test1.py
wxgfuntest/test2.py
wxgfuntest1.egg-info/PKG-INFO
wxgfuntest1.egg-info/SOURCES.txt
wxgfuntest1.egg-info/dependency_links.txt
wxgfuntest1.egg-info/not-zip-safe
wxgfuntest1.egg-info/top_level.txt