Metadata-Version: 1.0
Name: wxgfuntest1
Version: 0.3
Summary: The funniest joke in the world
Home-page: https://github.com/XGWang0/wxgfuntest
Author: Flying Circus
Author-email: flyingcircus@example.com
License: MIT
Platform: UNKNOWN
